AUTHORS
ChangeLog
LICENSE
README.rst
requirements-stdborg.txt
requirements.txt
setup.cfg
setup.py
stdborg.py
stdplugins/aesthetics.py
stdplugins/all.py
stdplugins/headpat.py
stdplugins/markdown.py
stdplugins/ninja.py
stdplugins/re.py
stdplugins/snip.py
uniborg/__init__.py
uniborg/_core.py
uniborg/hacks.py
uniborg/storage.py
uniborg/uniborg.py
uniborg/util.py
uniborg.egg-info/PKG-INFO
uniborg.egg-info/SOURCES.txt
uniborg.egg-info/dependency_links.txt
uniborg.egg-info/not-zip-safe
uniborg.egg-info/pbr.json
uniborg.egg-info/requires.txt
uniborg.egg-info/top_level.txt