Metadata-Version: 1.1
Name: uniborg
Version: 1.0.0.0.20190508120119
Summary: Telegram python bot using Telethon
Home-page: https://github.com/expectocode/uniborg
Author: Tanuj
Author-email: UNKNOWN
License: MPL2
Platform: UNKNOWN
Classifier: Environment :: Console
Classifier: Intended Audience :: Telecommunications Industry
Classifier: Operating System :: POSIX :: Linux
Classifier: Programming Language :: Python
Classifier: Programming Language :: Python :: 3
Classifier: Programming Language :: Unix Shell
Classifier: Topic :: Utilities
